hyrrokkin/__init__.py
hyrrokkin/api/__init__.py
hyrrokkin/api/link_type.py
hyrrokkin/api/node_type.py
hyrrokkin/api/package_type.py
hyrrokkin/api/port_type.py
hyrrokkin/api/schema_type.py
hyrrokkin/api/topology.py
hyrrokkin/api/topology_directory.py
hyrrokkin/api/topology_listener.py
hyrrokkin/apps/__init__.py
hyrrokkin/apps/designer.py
hyrrokkin/apps/directory.py
hyrrokkin/apps/options.toml
hyrrokkin/apps/topologies/example/topology.json
hyrrokkin/apps/topologies/example/node/n6ccd1b_0ccd73/properties.json
hyrrokkin/apps/topologies/example/node/n6cdf47_ef65e2/properties.json
hyrrokkin/apps/topologies/example/node/n6cff07_982e5a/properties.json
hyrrokkin/apps/topology/topology.json
hyrrokkin/apps/topology/node/fetch_collection0/properties.json
hyrrokkin/apps/topology/node/roi_extent0/properties.json
hyrrokkin/apps/topology/node/table_display_node0/properties.json
hyrrokkin/apps/topology/node/text_input_node0/properties.json
hyrrokkin/apps/topology/node/word_frequency_node0/properties.json
hyrrokkin/cli/__init__.py
hyrrokkin/cli/main.py
hyrrokkin/core/__init__.py
hyrrokkin/core/client.py
hyrrokkin/core/schema.py
hyrrokkin/core/serde.py
hyrrokkin/core/topology.py
hyrrokkin/core/topology_runner.py
hyrrokkin/engine_launchers/__init__.py
hyrrokkin/engine_launchers/engine_launcher.py
hyrrokkin/engine_launchers/javascript_engine_launcher.py
hyrrokkin/engine_launchers/python_engine_launcher.py
hyrrokkin/example_packages/__init__.py
hyrrokkin/example_packages/textgraph/__init__.py
hyrrokkin/example_packages/textgraph/javascript.json
hyrrokkin/example_packages/textgraph/python.json
hyrrokkin/example_packages/textgraph/schema.json
hyrrokkin/example_packages/textgraph/applications/__init__.py
hyrrokkin/example_packages/textgraph/applications/example.json
hyrrokkin/example_packages/textgraph/html/__init__.py
hyrrokkin/example_packages/textgraph/html/about.html
hyrrokkin/example_packages/textgraph/html/merge_frequencies_node.html
hyrrokkin-0.1.5.dist-info/licenses/LICENSE
hyrrokkin-0.1.5.dist-info/METADATA
hyrrokkin-0.1.5.dist-info/WHEEL
hyrrokkin-0.1.5.dist-info/entry_points.txt
hyrrokkin-0.1.5.dist-info/top_level.txt
hyrrokkin-0.1.5.dist-info/RECORD
