Metadata-Version: 2.4
Name: hyrrokkin
Version: 0.1.5
Summary: A lightweight asynchronous DAG execution engine for Python and other languages
Author-email: Visual Topology <dev@visualtopology.com>
License-Expression: MIT
Project-URL: Homepage, https://hyrrokk.in
Project-URL: Documentation, https://hyrrokk.in
Project-URL: Repository, https://codeberg.org/visual-topology/hyrrokkin
Project-URL: Issues, https://codeberg.org/visual-topology/hyrrokkin/issues
Project-URL: Changelog, https://codeberg.org/visual-topology/hyrrokkin/src/branch/main/CHANGELOG.md
Classifier: Programming Language :: Python :: 3
Classifier: Programming Language :: JavaScript
Classifier: Operating System :: POSIX :: Linux
Classifier: Topic :: Software Development :: Libraries :: Application Frameworks
Classifier: Development Status :: 3 - Alpha
Requires-Python: >=3.11
License-File: LICENSE
Provides-Extra: yaml
Requires-Dist: pyyaml; extra == "yaml"
Provides-Extra: validation
Requires-Dist: jsonschema; extra == "validation"
Provides-Extra: webapps
Requires-Dist: moonlette; extra == "webapps"
Provides-Extra: all
Requires-Dist: pyyaml; extra == "all"
Requires-Dist: jsonschema; extra == "all"
Requires-Dist: moonlette; extra == "all"
Dynamic: license-file
